TPEA/__init__.py
TPEA/__main__.py
TPEA/classify.py
TPEA/parsers.py
TPEA-1.1.27.dist-info/LICENSE
TPEA-1.1.27.dist-info/METADATA
TPEA-1.1.27.dist-info/WHEEL
TPEA-1.1.27.dist-info/top_level.txt
TPEA-1.1.27.dist-info/RECORD
