Metadata-Version: 2.1
Name: TPEA
Version: 1.1.27
Summary: Toolkit for Plant Endophyte Analyses
Author-email: Taikui Zhang <taikuizhang@hotmail.com>
Classifier: Programming Language :: Python :: 3
Classifier: License :: OSI Approved :: MIT License
Classifier: Operating System :: OS Independent
License-File: LICENSE
